houdinilab/__init__.py
houdinilab/scripts/json/courses.json
houdinilab/scripts/json/projects.json
houdinilab/scripts/python/pythonrc.py
houdinilab-0.1.1.dist-info/LICENSE
houdinilab-0.1.1.dist-info/METADATA
houdinilab-0.1.1.dist-info/WHEEL
houdinilab-0.1.1.dist-info/RECORD
