Metadata-Version: 2.1
Name: houdinilab
Version: 0.1.1
Summary: 
Author: Suhail
Author-email: suhailece@gmail.com
Requires-Python: >=3.11.7,<4.0.0
Classifier: Programming Language :: Python :: 3
Classifier: Programming Language :: Python :: 3.12
Classifier: Programming Language :: Python :: 3.13
Requires-Dist: matplotlib (>=3.10.3,<4.0.0)
Requires-Dist: numpy (>=2.2.6,<3.0.0)
Requires-Dist: oauthmanager (>=0.1.3,<0.2.0)
Requires-Dist: pandas (>=2.2.3,<3.0.0)
Requires-Dist: pypdf (>=5.5.0,<6.0.0)
Requires-Dist: scikit-learn (>=1.6.1,<2.0.0)
